timetrack/__init__.py
timetrack/config.py
timetrack/config.yml
timetrack/main.py
timetrack/outputs.py
timetrack/reports.py
timetrack/timeblock.py
timetrack/utils.py
timetrack/sounds/ding1.mp3
timetrack/sounds/ding2.mp3
timetrack/sounds/ding3.mp3
timetrack_cli-0.0.2.dist-info/entry_points.txt
timetrack_cli-0.0.2.dist-info/LICENSE
timetrack_cli-0.0.2.dist-info/WHEEL
timetrack_cli-0.0.2.dist-info/METADATA
timetrack_cli-0.0.2.dist-info/RECORD
